setup.py
distributions_na/Binomialdistribution.py
distributions_na/Gaussiandistribution.py
distributions_na/Generaldistribution.py
distributions_na/__init__.py
distributions_na.egg-info/PKG-INFO
distributions_na.egg-info/SOURCES.txt
distributions_na.egg-info/dependency_links.txt
distributions_na.egg-info/not-zip-safe
distributions_na.egg-info/top_level.txt